pyark.cpython-37m-darwin.so
pyark.dylibs/libboost_atomic-mt.dylib
pyark.dylibs/libboost_chrono-mt.dylib
pyark.dylibs/libboost_date_time-mt.dylib
pyark.dylibs/libboost_filesystem-mt.dylib
pyark.dylibs/libboost_system-mt.dylib
pyark.dylibs/libboost_thread-mt.dylib
pyark.dylibs/libfmt.9.1.0.dylib
pyark.dylibs/libjpeg.8.2.2.dylib
pyark.dylibs/liblz4.1.9.4.dylib
pyark.dylibs/libpng16.16.dylib
pyark.dylibs/libturbojpeg.0.2.0.dylib
pyark.dylibs/libxxhash.0.8.1.dylib
pyark.dylibs/libzstd.1.5.4.dylib
projectaria.oat-0.0.1.dist-info/METADATA
projectaria.oat-0.0.1.dist-info/WHEEL
projectaria.oat-0.0.1.dist-info/top_level.txt
projectaria.oat-0.0.1.dist-info/RECORD
