Metadata-Version: 2.1
Name: projectaria.oat
Version: 0.0.1
Summary: Python API for sensor models and streaming of Aria datasets.
Home-page: UNKNOWN
Author: Meta Reality Labs Research
License: UNKNOWN
Platform: UNKNOWN
Requires-Python: >=3.6
Provides-Extra: test
Requires-Dist: pytest (>=6.0) ; extra == 'test'
